aicaptcha/__init__.py
aicaptcha/api.py
aicaptcha/utils.py
aicaptcha-1.0.4.dist-info/LICENSE
aicaptcha-1.0.4.dist-info/METADATA
aicaptcha-1.0.4.dist-info/WHEEL
aicaptcha-1.0.4.dist-info/top_level.txt
aicaptcha-1.0.4.dist-info/RECORD
