Metadata-Version: 2.1
Name: aicaptcha
Version: 1.0.4
Summary: Python module for easy integration with AiCaptcha API
Home-page: https://github.com/Mr-Abood/AiCaptcha
Author: AiCaptcha
Author-email: abodawad1111@gmail.com
Classifier: Programming Language :: Python :: 3
Classifier: License :: OSI Approved :: MIT License
Classifier: Operating System :: OS Independent
Requires-Python: >=3.6
License-File: LICENSE
Requires-Dist: requests
